setup.py
distributions_gb_yr/Binomialdistribution.py
distributions_gb_yr/Gaussiandistribution.py
distributions_gb_yr/Generaldistribution.py
distributions_gb_yr/__init__.py
distributions_gb_yr.egg-info/PKG-INFO
distributions_gb_yr.egg-info/SOURCES.txt
distributions_gb_yr.egg-info/dependency_links.txt
distributions_gb_yr.egg-info/not-zip-safe
distributions_gb_yr.egg-info/top_level.txt