Metadata-Version: 1.0
Name: distributions-gb-yr
Version: 1.0
Summary: Gaussian distributions
Home-page: UNKNOWN
Author: Yash
Author-email: UNKNOWN
License: UNKNOWN
Platform: UNKNOWN
